{"slide_id":"P2-A18-2","hooks":[{"category":"Myth-Busting Hooks","template":"(insert item) (insert fact), (insert complete opposite item) (insert similar fact).","text":"Same currency, two prices today. One business owner pays more, the next pays less.","recommended":true},{"category":"Educational Hooks","template":"If you don't have (insert item/action), do (insert item/action).","text":"If a business owner pays suppliers on a personal rate, switch to the business rate.","recommended":false},{"category":"Storytelling Hooks","template":"Yesterday I was at (insert location) when I noticed something (insert adjective).","text":"A business owner checked his supplier wire and noticed something strange in the rate.","recommended":false},{"category":"Authority Hooks","template":"My customer/client got (insert dream result) without (insert pain point).","text":"One business owner saved 300 dollars per supplier wire without changing anything but the rate.","recommended":false},{"category":"Random Hooks","template":"(insert big brand) didn't want to sponsor this video, let me show you what they're missing out on.","text":"His bank never told him there were two rates. Watch what they hid.","recommended":false}]}